conduit/__init__.py
conduit/client/callbacks.py
conduit/client/coordinator.py
conduit/client/request_context.py
conduit/client/server_manager.py
conduit/client/session.py
conduit/client/protocol/__init__.py
conduit/client/protocol/elicitation.py
conduit/client/protocol/roots.py
conduit/client/protocol/sampling.py
conduit/protocol/__init__.py
conduit/protocol/base.py
conduit/protocol/common.py
conduit/protocol/completions.py
conduit/protocol/content.py
conduit/protocol/elicitation.py
conduit/protocol/initialization.py
conduit/protocol/jsonrpc.py
conduit/protocol/logging.py
conduit/protocol/prompts.py
conduit/protocol/resources.py
conduit/protocol/roots.py
conduit/protocol/sampling.py
conduit/protocol/tools.py
conduit/protocol/unions.py
conduit/server/callbacks.py
conduit/server/client_manager.py
conduit/server/coordinator.py
conduit/server/request_context.py
conduit/server/session.py
conduit/server/protocol/__init__.py
conduit/server/protocol/completions.py
conduit/server/protocol/logging.py
conduit/server/protocol/prompts.py
conduit/server/protocol/resources.py
conduit/server/protocol/tools.py
conduit/shared/__init__.py
conduit/shared/exceptions.py
conduit/shared/message_parser.py
conduit/shared/request_tracker.py
conduit/transport/__init__.py
conduit/transport/client.py
conduit/transport/client_v2.py
conduit/transport/server.py
conduit/transport/http/__init__.py
conduit/transport/http/sse.py
conduit/transport/http/client/__init__.py
conduit/transport/http/client/client.py
conduit/transport/http/client/client_message_sender.py
conduit/transport/http/client/client_stream_manager.py
conduit/transport/http/server/__init__.py
conduit/transport/http/server/connection_manager.py
conduit/transport/http/server/message_sender.py
conduit/transport/http/server/server_transport.py
conduit/transport/http/server/stream_manager.py
conduit/transport/stdio/__init__.py
conduit/transport/stdio/client.py
conduit/transport/stdio/client_v2.py
conduit/transport/stdio/server.py
conduit_mcp-0.0.1.dist-info/licenses/LICENSE
conduit_mcp-0.0.1.dist-info/METADATA
conduit_mcp-0.0.1.dist-info/WHEEL
conduit_mcp-0.0.1.dist-info/top_level.txt
conduit_mcp-0.0.1.dist-info/RECORD
