Metadata-Version: 2.4
Name: conduit-mcp
Version: 0.0.1
Summary: A Python SDK for Model Context Protocol (placeholder - coming soon!)
Author-email: Ian Davenport <davenport.ianc@gmail.com>
Keywords: mcp,model-context-protocol,sdk
Classifier: Development Status :: 1 - Planning
Classifier: License :: OSI Approved :: Apache Software License
Classifier: Programming Language :: Python :: 3.12
Requires-Python: >=3.12
License-File: LICENSE
Dynamic: license-file
